sunnah_api/__init__.py
sunnah_api/adaptor.py
sunnah_api/base.py
sunnah_api-0.3.1.dist-info/LICENSE
sunnah_api-0.3.1.dist-info/METADATA
sunnah_api-0.3.1.dist-info/WHEEL
sunnah_api-0.3.1.dist-info/top_level.txt
sunnah_api-0.3.1.dist-info/RECORD
